lda_over_time/__about__.py
lda_over_time/__init__.py
lda_over_time/lda_over_time.py
lda_over_time/models/__init__.py
lda_over_time/models/dtm_model_interface.py
lda_over_time/models/lda_seq_model.py
lda_over_time/models/temporal_lda_model.py
lda_over_time-0.2.0.dist-info/METADATA
lda_over_time-0.2.0.dist-info/WHEEL
lda_over_time-0.2.0.dist-info/licenses/COPYING
lda_over_time-0.2.0.dist-info/licenses/COPYING.LESSER
lda_over_time-0.2.0.dist-info/RECORD
