Metadata-Version: 2.1
Name: lda-over-time
Version: 0.2.0
Project-URL: Documentation, https://github.com/lda-over-time/lda-over-time#readme
Project-URL: Issues, https://github.com/lda-over-time/lda-over-time/issues
Project-URL: Source, https://github.com/lda-over-time/lda-over-time
Author-email: Willian Ozako <willian.ozako@gmail.com>
License-File: COPYING
License-File: COPYING.LESSER
Classifier: Development Status :: 3 - Alpha
Classifier: Operating System :: OS Independent
Classifier: Programming Language :: Python
Classifier: Programming Language :: Python :: 3.7
Classifier: Programming Language :: Python :: 3.8
Classifier: Programming Language :: Python :: 3.9
Classifier: Programming Language :: Python :: 3.10
Classifier: Programming Language :: Python :: 3.11
Classifier: Topic :: Scientific/Engineering
Classifier: Topic :: Scientific/Engineering :: Information Analysis
Classifier: Topic :: Scientific/Engineering :: Visualization
Requires-Python: >=3.7
Requires-Dist: gensim
Requires-Dist: pyldavis
Requires-Dist: seaborn
